{
  "경영학부": "https://biz.cnu.ac.kr/biz/sub05_01_01.do",
  "경제학과": "https://econ.cnu.ac.kr/econ/notice/undergraduate.do",
  "국어국문학과": "https://kor.cnu.ac.kr/kor/notice/notice1.do",
  "영어영문학과": "https://english.cnu.ac.kr/english/notice/undergraduate.do",
  "중어중문학과": "https://chinese.cnu.ac.kr/chinese/notice/undergraduate.do",
  "일어일문학과": "https://japanese.cnu.ac.kr/japanese/notice/undergraduate.do",
  "독어독문학과": "https://german.cnu.ac.kr/german/notice/undergraduate.do",
  "불어불문학과": "https://french.cnu.ac.kr/french/notice/undergraduate.do",
  "사학과": "https://history.cnu.ac.kr/history/notice/undergraduate.do",
  "철학과": "https://philo.cnu.ac.kr/philo/board/notice.do",
  "사회학과": "https://socio.cnu.ac.kr/socio/notice/undergraduate.do",
  "정치외교학과": "https://politics.cnu.ac.kr/politics/notice/undergraduate.do",
  "행정학과": "https://pa.cnu.ac.kr/pa/notice/notice.do",
  "문헌정보학과": "https://lis.cnu.ac.kr/lis/notice/undergraduate.do",
  "심리학과": "https://psych.cnu.ac.kr/psych/notice/undergraduate.do",
  "지리학과": "https://geo.cnu.ac.kr/geo/notice/undergraduate.do",
  "생명과학과": "https://biology.cnu.ac.kr/biology/notice/undergraduate.do",
  "수학과": "https://math.cnu.ac.kr/math/notice/undergraduate.do",
  "물리학과": "https://physics.cnu.ac.kr/physics/notice/undergraduate.do",
  "화학과": "https://chem.cnu.ac.kr/chem/undergrad/notice.do",
  "생명시스템학과": "https://biosys.cnu.ac.kr/biosys/notice/notice.do",
  "지질환경과학과": "https://geos.cnu.ac.kr/geos/notice/notice1.do",
  "간호학과": "https://nurse.cnu.ac.kr/nurse/board/notice_undergraduates.do",
  "의예과": "https://med.cnu.ac.kr/med/board/notice_undergraduate.do",
  "의학과": "https://med.cnu.ac.kr/med/board/notice_undergraduate.do",
  "치의예과": "https://dent.cnu.ac.kr/dent/undergraduate/notice.do",
  "치의학과": "https://dent.cnu.ac.kr/dent/undergraduate/notice.do",
  "수의예과": "https://vetmed.cnu.ac.kr/vetmed/undergrad/notice.do",
  "수의학과": "https://vetmed.cnu.ac.kr/vetmed/undergrad/notice.do",
  "건축공학과": "https://arch.cnu.ac.kr/arch/board/notice_undergraduate.do",
  "토목공학과": "https://civil.cnu.ac.kr/civil/notice/undergraduate.do",
  "환경공학과": "https://enve.cnu.ac.kr/enve/notice/undergraduate.do",
  "기계공학부": "https://me.cnu.ac.kr/me/notice/undergraduate.do",
  "항공우주공학과": "https://aerospace.cnu.ac.kr/aerospace/notice/bachelor_notice.do",
  "신소재공학과": "https://mse.cnu.ac.kr/mse/notice/undergraduate.do",
  "전기공학과": "https://ee.cnu.ac.kr/ee/notice/undergraduate.do",
  "전자공학과": "https://ee.cnu.ac.kr/ee/notice/undergraduate.do",
  "컴퓨터공학과": "https://cse.cnu.ac.kr/cse/notice/undergraduate.do",
  "화학공학과": "https://chemeng.cnu.ac.kr/chemeng/notice/undergraduate.do",
  "식품영양학과": "https://fnt.cnu.ac.kr/fnt/notice/undergraduate.do",
  "패키징학과": "https://packaging.cnu.ac.kr/packaging/notice/undergraduate.do",
  "바이오에너지공학과": "https://bioenergy.cnu.ac.kr/bioenergy/notice/undergraduate.do",
  "산림환경자원학과": "https://forest.cnu.ac.kr/forest/notice/notice_undergraduate.do",
  "조경학과": "https://landscape.cnu.ac.kr/landscape/notice/notice.do",
  "식물자원학과": "https://prc.cnu.ac.kr/prc/notice/undergraduate.do",
  "원예학과": "https://hort.cnu.ac.kr/hort/notice/undergraduate.do",
  "동물자원과학과": "https://anres.cnu.ac.kr/anres/notice/undergraduate.do",
  "경제학부(야)": "https://econ.cnu.ac.kr/econ/notice/undergraduate.do"
}
